euroscipy2017.py
euroscipy2017-0.2.dist-info/LICENSE
euroscipy2017-0.2.dist-info/WHEEL
euroscipy2017-0.2.dist-info/METADATA
euroscipy2017-0.2.dist-info/RECORD
